mews/__init__.py
mews/run_energyplus.py
mews/run_mews.py
mews/constants/__init__.py
mews/constants/analysis.py
mews/constants/data_format.py
mews/constants/physical.py
mews/cython/__init__.py
mews/cython/markov.cp313-win_amd64.pyd
mews/cython/markov.pyx
mews/cython/markov_time_dependent.cp313-win_amd64.pyd
mews/cython/markov_time_dependent.pyx
mews/data_requests/CMIP6.py
mews/data_requests/__init__.py
mews/data_requests/noaa.py
mews/epw/__init__.py
mews/epw/epw.py
mews/errors/__init__.py
mews/errors/exceptions.py
mews/events/__init__.py
mews/events/extreme_temperature_waves.py
mews/events/data/__init__.py
mews/graphics/__init__.py
mews/graphics/plotting2D.py
mews/stats/__init__.py
mews/stats/distributions.py
mews/stats/extreme.py
mews/stats/markov.py
mews/stats/markov_time_dependent.py
mews/stats/solve.py
mews/utilities/__init__.py
mews/utilities/utilities.py
mews/weather/__init__.py
mews/weather/alter.py
mews/weather/climate.py
mews/weather/doe2weather.py
mews/weather/psychrometrics.py
mews/weather/data/__init__.py
mews-1.1.3.dist-info/licenses/LICENSE.md
mews-1.1.3.dist-info/licenses/LICENSE.txt
mews-1.1.3.dist-info/METADATA
mews-1.1.3.dist-info/WHEEL
mews-1.1.3.dist-info/top_level.txt
mews-1.1.3.dist-info/RECORD
