Metadata-Version: 2.4
Name: MEWS
Version: 1.1.3
Summary: Heat wave stochastic generator using CMIP6, NOAA, and IPCC information
Author-email: "Daniel L. Villa" <dlvilla@sandia.gov>
Maintainer-email: "Daniel L. Villa" <dlvilla@sandia.gov>
License: Revised BSD
Project-URL: Repository, https://github.com/sandialabs/MEWS.git
Keywords: Building Energy Modeling,Infrastructure,Extreme Weather,Markov,Resilience,Energy Plus,DOE2,DOE-2
Requires-Python: >=3.9
License-File: LICENSE.md
License-File: LICENSE.txt
Requires-Dist: numpy
Requires-Dist: pandas
Requires-Dist: matplotlib
Requires-Dist: scipy
Requires-Dist: statsmodels
Requires-Dist: openpyxl
Requires-Dist: cython
Requires-Dist: xarray[complete]
Requires-Dist: CoolProp
Provides-Extra: test
Requires-Dist: pytest; extra == "test"
Requires-Dist: pytest-cov; extra == "test"
Provides-Extra: pylint
Requires-Dist: pylint; extra == "pylint"
Provides-Extra: docs
Requires-Dist: sphinx; extra == "docs"
Dynamic: license-file
